pypnf/__init__.py
pypnf/chart.py
pypnf/testdata.py
pypnf/data/AAPL.csv
pypnf/data/MSFT.csv
pypnf/data/^SPX.csv
pypnf-0.0.7.dist-info/LICENSE
pypnf-0.0.7.dist-info/METADATA
pypnf-0.0.7.dist-info/WHEEL
pypnf-0.0.7.dist-info/top_level.txt
pypnf-0.0.7.dist-info/RECORD
