Metadata-Version: 2.1
Name: pypnf
Version: 0.0.7
Summary: A Package for Point and Figure Charting
Home-page: https://github.com/swaschke/pypnf
Author: Stefan Waschke
Author-email: swaschke.pypnf@gmail.com
License: GPL2
Keywords: Point and Figure,PnF,Sentiment Indicator
Classifier: Development Status :: 4 - Beta
Classifier: Programming Language :: Python :: 3.6
Classifier: Programming Language :: Python :: 3.7
Classifier: Programming Language :: Python :: 3.8
Classifier: Programming Language :: Python :: 3.9
Classifier: License :: OSI Approved :: GNU General Public License v2 (GPLv2)
Classifier: Operating System :: OS Independent
Classifier: Topic :: Office/Business :: Financial
Requires-Python: >=3.6
License-File: LICENSE
Requires-Dist: numpy >=1.20
Requires-Dist: matplotlib >=3.7
Requires-Dist: tabulate >=0.8.9
